{
  "$schema": "https://json-schema.org/draft/2020-12/schema",
  "description": "Sample values of an associated image along tracks.\n\nBy default, the value of the underlying image at each point along the track is written to either an ASCII file (with all values for each track on the same line), or a track scalar file (.tsf). Alternatively, some statistic can be taken from the values along each streamline and written to a vector file.\n\nReferences:\n\n* If using -precise option: Smith, R. E.; Tournier, J.-D.; Calamante, F. & Connelly, A. SIFT: Spherical-deconvolution informed filtering of tractograms. NeuroImage, 2013, 67, 298-312",
  "type": "object",
  "properties": {
    "__STYXTYPE__": {
      "const": "tcksample"
    },
    "stat_tck": {
      "anyOf": [
        {
          "type": "string"
        },
        {
          "type": "null"
        }
      ],
      "default": null,
      "title": "stat_tck",
      "description": "compute some statistic from the values along each streamline (options are: mean,median,min,max)"
    },
    "nointerp": {
      "type": "boolean",
      "default": false,
      "title": "nointerp",
      "description": "do not use trilinear interpolation when sampling image values"
    },
    "precise": {
      "type": "boolean",
      "default": false,
      "title": "precise",
      "description": "use the precise mechanism for mapping streamlines to voxels (obviates the need for trilinear interpolation) (only applicable if some per-streamline statistic is requested)"
    },
    "use_tdi_fraction": {
      "type": "boolean",
      "default": false,
      "title": "use_tdi_fraction",
      "description": "each streamline is assigned a fraction of the image intensity in each voxel based on the fraction of the track density contributed by that streamline (this is only appropriate for processing a whole-brain tractogram, and images for which the quantiative parameter is additive)"
    },
    "info": {
      "type": "boolean",
      "default": false,
      "title": "info",
      "description": "display information messages."
    },
    "quiet": {
      "type": "boolean",
      "default": false,
      "title": "quiet",
      "description": "do not display information messages or progress status; alternatively, this can be achieved by setting the MRTRIX_QUIET environment variable to a non-empty string."
    },
    "debug": {
      "type": "boolean",
      "default": false,
      "title": "debug",
      "description": "display debugging messages."
    },
    "force": {
      "type": "boolean",
      "default": false,
      "title": "force",
      "description": "force overwrite of output files (caution: using the same file as input and output might cause unexpected behaviour)."
    },
    "nthreads": {
      "anyOf": [
        {
          "type": "integer"
        },
        {
          "type": "null"
        }
      ],
      "default": null,
      "title": "nthreads",
      "description": "use this number of threads in multi-threaded applications (set to 0 to disable multi-threading)."
    },
    "config": {
      "anyOf": [
        {
          "type": "array",
          "items": {
            "type": "object",
            "properties": {
              "__STYXTYPE__": {
                "const": "config"
              },
              "key": {
                "type": "string",
                "title": "key",
                "description": "temporarily set the value of an MRtrix config file entry."
              },
              "value": {
                "type": "string",
                "title": "value",
                "description": "temporarily set the value of an MRtrix config file entry."
              }
            },
            "additionalProperties": false,
            "description": "temporarily set the value of an MRtrix config file entry.",
            "required": [
              "key",
              "value"
            ]
          }
        },
        {
          "type": "null"
        }
      ],
      "default": null,
      "description": "temporarily set the value of an MRtrix config file entry."
    },
    "help": {
      "type": "boolean",
      "default": false,
      "title": "help",
      "description": "display this information page and exit."
    },
    "version": {
      "type": "boolean",
      "default": false,
      "title": "version",
      "description": "display version information and exit."
    },
    "tracks": {
      "type": "string",
      "title": "tracks",
      "description": "the input track file"
    },
    "image": {
      "type": "string",
      "title": "image",
      "description": "the image to be sampled"
    },
    "values": {
      "type": "string",
      "title": "values",
      "description": "the output sampled values"
    }
  },
  "additionalProperties": false,
  "required": [
    "tracks",
    "image",
    "values"
  ]
}