{
  "$schema": "https://json-schema.org/draft/2020-12/schema",
  "title": "transformconvert",
  "description": "Convert linear transformation matrices.\n\nThis command allows to convert transformation matrices provided by other registration softwares to a format usable in MRtrix3. Example usages are provided below.\n\nReferences:\n\n",
  "type": "object",
  "additionalProperties": false,
  "properties": {
    "root": {
      "type": "string",
      "title": "Root",
      "description": "Output root directory"
    },
    "output": {
      "type": "string",
      "title": "output",
      "description": "the output transformation matrix."
    }
  }
}