{
  "$schema": "https://json-schema.org/draft/2020-12/schema",
  "title": "warpcorrect",
  "description": "Replaces voxels in a deformation field that point to a specific out of bounds location with nan,nan,nan.\n\nThis can be used in conjunction with the warpinit command to compute a MRtrix compatible deformation field from non-linear transformations generated by any other registration package.\n\nReferences:\n\n",
  "type": "object",
  "additionalProperties": false,
  "properties": {
    "root": {
      "type": "string",
      "title": "Root",
      "description": "Output root directory"
    },
    "out": {
      "type": "string",
      "title": "out",
      "description": "the output warp image."
    }
  }
}