{
  "$schema": "https://json-schema.org/draft/2020-12/schema",
  "title": "antsMotionCorr",
  "description": "ANTS Motion Correction application to perform motion correction on 4D time series data.",
  "type": "object",
  "additionalProperties": false,
  "properties": {
    "root": {
      "type": "string",
      "title": "Root",
      "description": "Output root directory"
    },
    "output_transform_prefix": {
      "type": "string",
      "title": "Output transform prefix",
      "description": "The output is the transformation matrix."
    },
    "warped_image": {
      "type": "string",
      "title": "Warped Image",
      "description": "The output is the warped moving image."
    },
    "average_image_output": {
      "type": "string",
      "title": "Average Image Output",
      "description": "The output is the averaged image of the input time series."
    }
  }
}