{
  "$schema": "https://json-schema.org/draft/2020-12/schema",
  "description": "Program to estimate the probability of false positive (noise-only) clusters.",
  "type": "object",
  "properties": {
    "@type": {
      "const": "afni.3dClustSim"
    },
    "nxyz": {
      "anyOf": [
        {
          "type": "string"
        },
        {
          "type": "null"
        }
      ],
      "default": null,
      "title": "Grid Size",
      "description": "Size of 3D grid to use for simulation"
    },
    "dxyz": {
      "anyOf": [
        {
          "type": "string"
        },
        {
          "type": "null"
        }
      ],
      "default": null,
      "title": "Voxel Sizes",
      "description": "Voxel sizes along each dimension"
    },
    "ball": {
      "type": "boolean",
      "default": false,
      "title": "Ball Mask",
      "description": "Mask off points outside a ball at the center of the grid"
    },
    "mask": {
      "anyOf": [
        {
          "type": "string"
        },
        {
          "type": "null"
        }
      ],
      "default": null,
      "title": "Mask Dataset",
      "description": "Use the 0 sub-brick of this dataset as a mask"
    },
    "oksmallmask": {
      "type": "boolean",
      "default": false,
      "title": "Allow Small Mask",
      "description": "Allow small masks with less than 128 nonzero voxels"
    },
    "inset": {
      "anyOf": [
        {
          "type": "array",
          "items": {
            "type": "string"
          }
        },
        {
          "type": "null"
        }
      ],
      "default": null,
      "title": "Input Datasets",
      "description": "Use these dataset(s) as the simulations to threshold and clusterize"
    },
    "fwhm": {
      "anyOf": [
        {
          "type": "number"
        },
        {
          "type": "null"
        }
      ],
      "default": null,
      "title": "Gaussian Filter Width",
      "description": "Gaussian filter width in mm (use -fwhmxyz for different values per axis)"
    },
    "acf": {
      "anyOf": [
        {
          "type": "string"
        },
        {
          "type": "null"
        }
      ],
      "default": null,
      "title": "Autocorrelation Function",
      "description": "Parameters a, b, c for the autocorrelation function"
    },
    "nopad": {
      "type": "boolean",
      "default": false,
      "title": "No Padding",
      "description": "Turn off padding slices added for edge effects"
    },
    "pthr": {
      "anyOf": [
        {
          "type": "string"
        },
        {
          "type": "null"
        }
      ],
      "default": null,
      "title": "P-Value Thresholds",
      "description": "List of uncorrected per voxel p-values"
    },
    "athr": {
      "anyOf": [
        {
          "type": "string"
        },
        {
          "type": "null"
        }
      ],
      "default": null,
      "title": "Alpha Thresholds",
      "description": "List of corrected whole volume alpha-values"
    },
    "lots": {
      "type": "boolean",
      "default": false,
      "title": "Lots of Values",
      "description": "Use a longer list of values for pthr and athr"
    },
    "mega": {
      "type": "boolean",
      "default": false,
      "title": "Mega Values",
      "description": "Add even more values to the pthr and athr grids"
    },
    "iter": {
      "anyOf": [
        {
          "type": "number"
        },
        {
          "type": "null"
        }
      ],
      "default": null,
      "title": "Monte Carlo Iterations",
      "description": "Number of Monte Carlo simulations"
    },
    "nodec": {
      "type": "boolean",
      "default": false,
      "title": "No Decimal",
      "description": "Print the cluster size threshold as an integer"
    },
    "seed": {
      "anyOf": [
        {
          "type": "number"
        },
        {
          "type": "null"
        }
      ],
      "default": null,
      "title": "Random Seed",
      "description": "Random number seed"
    },
    "niml": {
      "type": "boolean",
      "default": false,
      "title": "NIML Output",
      "description": "Output the table in XML/NIML format"
    },
    "both": {
      "type": "boolean",
      "default": false,
      "title": "Both Formats",
      "description": "Output the table in both XML/NIML format and in .1D format"
    },
    "prefix": {
      "anyOf": [
        {
          "type": "string"
        },
        {
          "type": "null"
        }
      ],
      "default": null,
      "title": "Output Prefix",
      "description": "Specify prefix for the output files"
    },
    "cmd": {
      "anyOf": [
        {
          "type": "string"
        },
        {
          "type": "null"
        }
      ],
      "default": null,
      "title": "Command File",
      "description": "Write command for putting results into a file's header"
    },
    "quiet": {
      "type": "boolean",
      "default": false,
      "title": "Quiet Mode",
      "description": "Don't print out progress reports"
    },
    "ssave": {
      "anyOf": [
        {
          "type": "string"
        },
        {
          "type": "null"
        }
      ],
      "default": null,
      "title": "Save Random Volumes",
      "description": "Save un-thresholded generated random volumes"
    }
  },
  "additionalProperties": false
}