{
  "$schema": "https://json-schema.org/draft/2020-12/schema",
  "title": "fim2",
  "description": "Functional Imaging Mapping Tool",
  "type": "object",
  "additionalProperties": false,
  "properties": {
    "root": {
      "type": "string",
      "title": "Root",
      "description": "Output root directory"
    },
    "activation_magnitudes": {
      "type": "string",
      "title": "Activation Magnitudes File",
      "description": "Activation magnitudes output file"
    },
    "correlation_image": {
      "type": "string",
      "title": "Correlation Image File",
      "description": "Correlation image output file"
    },
    "contrast_to_noise_image": {
      "type": "string",
      "title": "Contrast-to-Noise Image File",
      "description": "Contrast-to-noise image output file"
    },
    "std_deviation_image": {
      "type": "string",
      "title": "Standard Deviation Image File",
      "description": "Standard deviation image output file"
    },
    "ls_fit_coefficients": {
      "type": "string",
      "title": "LS Fit Coefficients Files",
      "description": "Least squares fit coefficients image files"
    },
    "subtracted_references": {
      "type": "string",
      "title": "Subtracted References Time Series Files",
      "description": "Subtracted ortho reference time series images"
    }
  }
}