{
  "$schema": "https://json-schema.org/draft/2020-12/schema",
  "title": "3dEigsToDT",
  "description": "Convert set of DTI eigenvectors and eigenvalues to a diffusion tensor, with optional value-scaling and vector-flipping.",
  "type": "object",
  "additionalProperties": false,
  "properties": {
    "root": {
      "type": "string",
      "title": "Root",
      "description": "Output root directory"
    },
    "dt_brik_output": {
      "type": "string",
      "title": "Output DT BRIK File",
      "description": "Output diffusion tensor (DT) file in AFNI format (BRIK)"
    },
    "dt_head_output": {
      "type": "string",
      "title": "Output DT HEAD File",
      "description": "Output diffusion tensor (DT) file in AFNI format (HEAD)"
    }
  }
}