{
  "$schema": "https://json-schema.org/draft/2020-12/schema",
  "title": "@CheckForAfniDset",
  "description": "Check for the existence of AFNI datasets.",
  "type": "object",
  "additionalProperties": false,
  "properties": {
    "root": {
      "type": "string",
      "title": "Root",
      "description": "Output root directory"
    },
    "output_status": {
      "type": "string",
      "title": "Output Status",
      "description": "Text file containing the status code of the dataset"
    }
  }
}