{
  "$schema": "https://json-schema.org/draft/2020-12/schema",
  "description": "Tool to calculate the distance between the centers of two datasets",
  "type": "object",
  "properties": {
    "@type": {
      "const": "afni.@Center_Distance"
    },
    "dset1": {
      "type": "string",
      "title": "Dataset 1",
      "description": "First dataset file (e.g. file1.nii.gz)"
    },
    "dset2": {
      "type": "string",
      "title": "Dataset 2",
      "description": "Second dataset file (e.g. file2.nii.gz)"
    }
  },
  "additionalProperties": false,
  "required": [
    "dset1",
    "dset2"
  ]
}