{
  "$schema": "https://json-schema.org/draft/2020-12/schema",
  "description": "A script for longitudinal segmentation of the hippocampal/amygdala regions",
  "type": "object",
  "properties": {
    "__STYXTYPE__": {
      "const": "segmentHA_T1_long.sh"
    },
    "subject_dir": {
      "type": "string",
      "title": "Subject Directory",
      "description": "Directory containing subject data"
    },
    "subject_id": {
      "type": "string",
      "title": "Subject ID",
      "description": "Identifier for the subject within the subject directory"
    }
  },
  "additionalProperties": false,
  "required": [
    "subject_dir",
    "subject_id"
  ]
}