{
  "$schema": "https://json-schema.org/draft/2020-12/schema",
  "description": "A tool for anatomical segmentation using graph-based methods.",
  "type": "object",
  "properties": {
    "__STYXTYPE__": {
      "const": "anatomiCutsUtils"
    },
    "modules": {
      "anyOf": [
        {
          "type": "array",
          "items": {
            "type": "string"
          }
        },
        {
          "type": "null"
        }
      ],
      "default": null,
      "title": "Modules",
      "description": "Specify the modules to import for processing. Ensure necessary modules like 'graph_tools' are installed."
    }
  },
  "additionalProperties": false
}