{
  "$schema": "https://json-schema.org/draft/2020-12/schema",
  "description": "Tool for correcting motion in MRI scans",
  "type": "object",
  "properties": {
    "__STYXTYPE__": {
      "const": "mri_motion_correct"
    },
    "outfile": {
      "type": "string",
      "title": "Output file",
      "description": "Output file where the corrected MRI image(s) will be stored."
    },
    "infiles": {
      "type": "array",
      "items": {
        "type": "string"
      },
      "title": "Input files",
      "description": "Input MRI image files to be corrected."
    }
  },
  "additionalProperties": false,
  "required": [
    "outfile",
    "infiles"
  ]
}