{
  "$schema": "https://json-schema.org/draft/2020-12/schema",
  "title": "make_average_subcort",
  "description": "This creates an average subcortical mask for the given input subjects, intended for use in subcortical analysis in FSFAST to exclude cortical voxels.",
  "type": "object",
  "additionalProperties": false,
  "properties": {
    "root": {
      "type": "string",
      "title": "Root",
      "description": "Output root directory"
    },
    "output_mask_file": {
      "type": "string",
      "title": "Output Mask File",
      "description": "Final average subcortical mask in fsaverage/mni305 space"
    }
  }
}