{
  "$schema": "https://json-schema.org/draft/2020-12/schema",
  "title": "fs_temp_dir",
  "description": "Generates and creates an empty temporary directory",
  "type": "object",
  "properties": {
    "@type": {
      "const": "freesurfer.fs_temp_dir"
    },
    "base_directory": {
      "anyOf": [
        {
          "type": "string"
        },
        {
          "type": "null"
        }
      ],
      "default": null,
      "title": "Base Directory",
      "description": "Manually specify base temporary directory."
    },
    "scratch": {
      "type": "boolean",
      "default": false,
      "title": "Scratch Flag",
      "description": "Use /scratch directory if available, but FS_TMPDIR takes priority."
    }
  },
  "additionalProperties": false
}