{
  "$schema": "https://json-schema.org/draft/2020-12/schema",
  "title": "mrisp_paint",
  "description": "A tool for extracting arrays from a surface-registration template file and sampling them onto a surface mesh.",
  "type": "object",
  "additionalProperties": false,
  "properties": {
    "root": {
      "type": "string",
      "title": "Root",
      "description": "Output root directory"
    },
    "output_file": {
      "type": "string",
      "title": "Output file",
      "description": "Output file containing a surface-worth of per-vertex values in 'curvature' format."
    }
  }
}