{
  "$schema": "https://json-schema.org/draft/2020-12/schema",
  "title": "mris_mef_surfaces",
  "description": "Positions the tessellation of the cortical surface at the white matter surface, then the gray matter surface and generates surface files for these surfaces. Also generates 'curvature' file for cortical thickness and a surface file approximating layer IV of the cortical sheet.",
  "type": "object",
  "additionalProperties": false,
  "properties": {
    "root": {
      "type": "string",
      "title": "Root",
      "description": "Output root directory"
    }
  }
}