{
  "$schema": "https://json-schema.org/draft/2020-12/schema",
  "title": "mri_easyreg",
  "description": "EasyReg: deep learning registration simple and easy",
  "type": "object",
  "additionalProperties": false,
  "properties": {
    "root": {
      "type": "string",
      "title": "Root",
      "description": "Output root directory"
    },
    "registered_reference_output": {
      "type": "string",
      "title": "Registered Reference Output",
      "description": "Output registered reference image"
    },
    "registered_floating_output": {
      "type": "string",
      "title": "Registered Floating Output",
      "description": "Output registered floating image"
    },
    "forward_field_output": {
      "type": "string",
      "title": "Forward Field Output",
      "description": "Output forward field file"
    },
    "inverse_field_output": {
      "type": "string",
      "title": "Inverse Field Output",
      "description": "Output inverse field file"
    }
  }
}