{
  "$schema": "https://json-schema.org/draft/2020-12/schema",
  "title": "inflate_subject_new-lh",
  "description": "Tool for inflating the left hemisphere of a subject in FreeSurfer.",
  "type": "object",
  "properties": {
    "@type": {
      "const": "freesurfer.inflate_subject_new-lh"
    },
    "subject_dir": {
      "type": "string",
      "title": "Subject Directory",
      "description": "Directory of the subject's data in FreeSurfer"
    }
  },
  "additionalProperties": false,
  "required": [
    "subject_dir"
  ]
}