{
  "$schema": "https://json-schema.org/draft/2020-12/schema",
  "title": "dmri_stats_ac",
  "description": "The tool 'dmri_stats_ac' performs statistical analysis on dMRI data.",
  "type": "object",
  "additionalProperties": false,
  "properties": {
    "root": {
      "type": "string",
      "title": "Root",
      "description": "Output root directory"
    },
    "output_file": {
      "type": "string",
      "title": "Output File",
      "description": "Output of the dMRI statistical analysis"
    }
  }
}