{
  "$schema": "https://json-schema.org/draft/2020-12/schema",
  "title": "mri_stats2seg",
  "description": "A command-line tool for converting MRI statistical maps to segmented volume.",
  "type": "object",
  "additionalProperties": false,
  "properties": {
    "root": {
      "type": "string",
      "title": "Root",
      "description": "Output root directory"
    },
    "segmented_output": {
      "type": "string",
      "title": "Segmented Output File",
      "description": "Output segmented file."
    }
  }
}