{
  "$schema": "https://json-schema.org/draft/2020-12/schema",
  "title": "fvcompare",
  "description": "Simultaneously loads volume, segmentation, and surface data from two subjects in freeview, for comparing across time or different analysis methods.",
  "type": "object",
  "properties": {
    "@type": {
      "const": "freesurfer.fvcompare"
    },
    "subject1": {
      "type": "string",
      "title": "Subject 1",
      "description": "Subject 1 identifier"
    },
    "subject2": {
      "type": "string",
      "title": "Subject 2",
      "description": "Subject 2 identifier"
    },
    "subject_dir1": {
      "anyOf": [
        {
          "type": "string"
        },
        {
          "type": "null"
        }
      ],
      "default": null,
      "title": "Subject Directory 1",
      "description": "Directory path for Subject 1"
    },
    "subject_dir2": {
      "anyOf": [
        {
          "type": "string"
        },
        {
          "type": "null"
        }
      ],
      "default": null,
      "title": "Subject Directory 2",
      "description": "Directory path for Subject 2"
    },
    "name1": {
      "anyOf": [
        {
          "type": "string"
        },
        {
          "type": "null"
        }
      ],
      "default": null,
      "title": "Name 1",
      "description": "Name associated with Subject 1 (default: s1)"
    },
    "name2": {
      "anyOf": [
        {
          "type": "string"
        },
        {
          "type": "null"
        }
      ],
      "default": null,
      "title": "Name 2",
      "description": "Name associated with Subject 2 (default: s2)"
    },
    "color1": {
      "anyOf": [
        {
          "type": "string"
        },
        {
          "type": "null"
        }
      ],
      "default": null,
      "title": "Surface Colors 1",
      "description": "Set surface colors for Subject 1"
    },
    "volume": {
      "anyOf": [
        {
          "type": "string"
        },
        {
          "type": "null"
        }
      ],
      "default": null,
      "title": "Volume Name",
      "description": "Volume name found in subject/mri (default: brainmask.mgz, can have multiple)"
    },
    "segmentation": {
      "anyOf": [
        {
          "type": "string"
        },
        {
          "type": "null"
        }
      ],
      "default": null,
      "title": "Segmentation Name",
      "description": "Segmentation name found in subject/mri (default: aparc+aseg.mgz, can have multiple)"
    },
    "aseg": {
      "type": "boolean",
      "default": false,
      "title": "Aseg Flag",
      "description": "Add aseg.mgz to segmentation list"
    },
    "no_seg": {
      "type": "boolean",
      "default": false,
      "title": "No Segmentation Flag",
      "description": "Do not display segmentations"
    },
    "left_hemi": {
      "type": "boolean",
      "default": false,
      "title": "Left Hemisphere Flag",
      "description": "Only display left hemisphere"
    },
    "right_hemi": {
      "type": "boolean",
      "default": false,
      "title": "Right Hemisphere Flag",
      "description": "Only display right hemisphere"
    },
    "no_surf": {
      "type": "boolean",
      "default": false,
      "title": "No Surface Flag",
      "description": "Do not display surfaces"
    },
    "gray_levels": {
      "anyOf": [
        {
          "type": "array",
          "items": {
            "type": "number"
          },
          "minItems": 2,
          "maxItems": 2
        },
        {
          "type": "null"
        }
      ],
      "default": null,
      "title": "Gray Scale Levels",
      "description": "Set gray scale levels"
    },
    "cursor_position": {
      "anyOf": [
        {
          "type": "array",
          "items": {
            "type": "number"
          },
          "minItems": 3,
          "maxItems": 3
        },
        {
          "type": "null"
        }
      ],
      "default": null,
      "title": "Cursor Position",
      "description": "Place cursor at given location and center Field of View"
    },
    "zoom_level": {
      "anyOf": [
        {
          "type": "number"
        },
        {
          "type": "null"
        }
      ],
      "default": null,
      "title": "Zoom Level",
      "description": "Set zoom level"
    },
    "annotation": {
      "anyOf": [
        {
          "type": "string"
        },
        {
          "type": "null"
        }
      ],
      "default": null,
      "title": "Annotation",
      "description": "Load annotation onto surfaces"
    },
    "aparc": {
      "type": "boolean",
      "default": false,
      "title": "Aparc Flag",
      "description": "Load aparc.annot onto surfaces"
    },
    "inflated": {
      "type": "boolean",
      "default": false,
      "title": "Inflated Surfaces Flag",
      "description": "Load inflated surfaces in addition to white and pial"
    },
    "white": {
      "type": "boolean",
      "default": false,
      "title": "White Surfaces Flag",
      "description": "Only show white surfaces"
    },
    "orig": {
      "type": "boolean",
      "default": false,
      "title": "Original Surfaces Flag",
      "description": "Only show orig.nofix and orig surfaces"
    },
    "surf_name": {
      "anyOf": [
        {
          "type": "string"
        },
        {
          "type": "null"
        }
      ],
      "default": null,
      "title": "Surf Name",
      "description": "Only show specified surface name"
    },
    "pointset": {
      "anyOf": [
        {
          "type": "string",
          "x-styx-type": "file"
        },
        {
          "type": "null"
        }
      ],
      "default": null,
      "title": "Point Set",
      "description": "Load point set file"
    },
    "wot2": {
      "type": "boolean",
      "default": false,
      "title": "WOT2 Surfaces Flag",
      "description": "Include the ?h.woT2.pial surfs"
    }
  },
  "additionalProperties": false,
  "required": [
    "subject1",
    "subject2"
  ]
}