{
  "$schema": "https://json-schema.org/draft/2020-12/schema",
  "title": "fslcomplex",
  "description": "Tool for manipulating complex-valued MR data",
  "type": "object",
  "additionalProperties": false,
  "properties": {
    "root": {
      "type": "string",
      "title": "Root",
      "description": "Output root directory"
    },
    "result_output_file": {
      "type": "string",
      "title": "Result output file",
      "description": "The resulting output file from the specified operation."
    }
  }
}