{
  "$schema": "https://json-schema.org/draft/2020-12/schema",
  "title": "tbss_deproject",
  "description": "Tool to deproject images from skeleton space to final space",
  "type": "object",
  "additionalProperties": false,
  "properties": {
    "root": {
      "type": "string",
      "title": "Root",
      "description": "Output root directory"
    },
    "stats_output": {
      "type": "string",
      "title": "Stats output",
      "description": "Output in stats directory."
    },
    "fa_output": {
      "type": "string",
      "title": "FA output",
      "description": "Output in FA directory."
    }
  }
}